{"cameraMode":{"drawMode":0,"name":"Shaded","section":"Shading Mode"},"sceneLighting":true,"audioPlay":false,"sceneViewState":{"m_AlwaysRefresh":false,"showFog":true,"showSkybox":true,"showFlares":true,"showImageEffects":true,"showParticleSystems":true,"showVisualEffectGraphs":true,"m_FxEnabled":true},"in2DMode":false,"pivot":{"x":0.7173192501068115,"y":3.3933522701263429,"z":-0.6796090006828308},"rotation":{"x":0.006300503853708506,"y":-0.0539768747985363,"z":0.00034086633240804076,"w":0.9985328316688538},"size":3.1553330421447756,"orthographic":false}